docker_compose_ex/__init__.py
docker_compose_ex/compose_ext.py
docker_compose_ex-0.1.0.dist-info/entry_points.txt
docker_compose_ex-0.1.0.dist-info/WHEEL
docker_compose_ex-0.1.0.dist-info/METADATA
docker_compose_ex-0.1.0.dist-info/RECORD
