Metadata-Version: 2.1
Name: docker-compose-ex
Version: 0.1.0
Summary: Docker Compose with `extends` option
Home-page: https://github.com/vitalik/docker-compose-ex
Author: Vitaliy Kucheryaviy
Author-email: ppr.vitaly@gmail.com
Requires-Python: >=3.5,<4.0
Classifier: Programming Language :: Python :: 3
Classifier: Programming Language :: Python :: 3.5
Classifier: Programming Language :: Python :: 3.6
Classifier: Programming Language :: Python :: 3.7
Requires-Dist: pyyaml (>=5.1,<6.0)
